{
  "metas": [
    {
      "id": "tt7959138",
      "type": "movie",
      "name": "10 Zivota ( Sr ).mp4 -  575.6 MB"
    },
    {
      "id": "tt3975918",
      "type": "movie",
      "name": "13 The Musical ( Hr ).mp4 -  903.3 MB"
    },
    {
      "id": "tt0055254",
      "type": "movie",
      "name": "101 Dalmatinac 01 ( H i S ).mp4 -  729.4 MB"
    },
    {
      "id": "tt0115433",
      "type": "movie",
      "name": "101 Dalmatinac 02 ( Sr ).mp4 -  574.3 MB"
    },
    {
      "id": "tt22527810",
      "type": "movie",
      "name": "12 Dana Bozica ( H I S ).mp4 -  192.3 MB"
    },
    {
      "id": "tt6570098",
      "type": "movie",
      "name": "Ainbo ( H i S ).mp4 -  662.4 MB"
    },
    {
      "id": "tt0821787",
      "type": "movie",
      "name": "Ajvanho ( Hr ).mp4 -  475.6 MB"
    },
    {
      "id": "tt0821787",
      "type": "movie",
      "name": "Ajvanho ( Sr ).mp4 -  648.6 MB"
    },
    {
      "id": "tt20857676",
      "type": "movie",
      "name": "Akademija Gospodina Kleksa ( Hr ) -  927.7 MB"
    },
    {
      "id": "tt1690100",
      "type": "movie",
      "name": "Aladin ( H i S ).mp4 -  805.5 MB"
    },
    {
      "id": "tt6139732",
      "type": "movie",
      "name": "Aladin 2019 ( film H I S ).mp4 -  1.2 GB"
    },
    {
      "id": "tt0115491",
      "type": "movie",
      "name": "Aladin Kralj Lopova ( Hr ).mp4 -  610.0 MB"
    },
    {
      "id": "tt0107952",
      "type": "movie",
      "name": "Aladin Povratak Dzafara ( H i S ).mp4 -  602.3 MB"
    },
    {
      "id": "tt4144206",
      "type": "movie",
      "name": "Albert ( H i S ).mp4 -  347.7 MB"
    },
    {
      "id": "tt1213012",
      "type": "movie",
      "name": "Alfa I Omega ( H I S ).mp4 -  813.7 MB"
    },
    {
      "id": "tt1742023",
      "type": "movie",
      "name": "Americano ( H i S ).mp4 -  739.4 MB"
    },
    {
      "id": "tt1985949",
      "type": "movie",
      "name": "Angry Birds 01 ( H I S ).mp4 -  1.0 GB"
    },
    {
      "id": "tt6095472",
      "type": "movie",
      "name": "Angry Birds 02 ( H I S ).mp4 -  949.3 MB"
    },
    {
      "id": "tt15520090",
      "type": "movie",
      "name": "Anka ( Hr ).mp4 -  597.7 MB"
    },
    {
      "id": "tt18933570",
      "type": "movie",
      "name": "Arci ( H i S ).mp4 -  840.4 MB"
    },
    {
      "id": "tt1430607",
      "type": "movie",
      "name": "Artur Bozic ( H I S ).mp4 -  909.3 MB"
    },
    {
      "id": "tt0072901",
      "type": "movie",
      "name": "Asterix I Obelix 12 Zadataka ( H I S ).mp4 -  830.4 MB"
    },
    {
      "id": "tt0088748",
      "type": "movie",
      "name": "Asterix I Obelix Gal ( H I S ).mp4 -  783.2 MB"
    },
    {
      "id": "tt3759416",
      "type": "movie",
      "name": "Asterix I Obelix Grad Bogova ( H I S ).mp4 -  540.4 MB"
    },
    {
      "id": "tt0250223",
      "type": "movie",
      "name": "Asterix I Obelix Kleopatra ( H I S ).mp4 -  819.6 MB"
    },
    {
      "id": "tt1597522",
      "type": "movie",
      "name": "Asterix I Obelix U Britaniji ( H i S ).mp4 -  786.8 MB"
    },
    {
      "id": "tt0096842",
      "type": "movie",
      "name": "Asterix I Obelix Velika Bitka ( H I S ).mp4 -  831.4 MB"
    },
    {
      "id": "tt0371552",
      "type": "movie",
      "name": "Asterix I Obelix Vikinzi ( H i S ).mp4 -  577.0 MB"
    },
    {
      "id": "tt0375568",
      "type": "movie",
      "name": "Astro Boy ( Hr ).mp4 -  734.7 MB"
    },
    {
      "id": "tt0230011",
      "type": "movie",
      "name": "Atlantida Izgubljeno Carstvo ( Sr ).mp4 -  586.5 MB"
    },
    {
      "id": "tt0093748",
      "type": "movie",
      "name": "Automobili 01 ( H i S ).mp4 -  1.3 GB"
    },
    {
      "id": "tt14039582",
      "type": "movie",
      "name": "Automobili 02 ( Hr ).mp4 -  912.8 MB"
    },
    {
      "id": "tt0245429",
      "type": "movie",
      "name": "Avanture Male Chihiro ( H I S ).mp4 -  904.8 MB"
    },
    {
      "id": "tt8816708",
      "type": "movie",
      "name": "Avanture Malog Don Kihota ( Hr ).mp4 -  913.7 MB"
    },
    {
      "id": "tt1764625",
      "type": "movie",
      "name": "Avanture Neustrasivog Teda ( H I S ).mp4 -  852.8 MB"
    },
    {
      "id": "tt1691917",
      "type": "movie",
      "name": "Avioni 01 ( H i S ).mp4 -  782.7 MB"
    },
    {
      "id": "tt2980706",
      "type": "movie",
      "name": "Avioni 02 Nebeski Vatrogasci ( H i S ).mp4 -  784.2 MB"
    },
    {
      "id": "tt1184384",
      "type": "movie",
      "name": "Badnja Svjetlost ( Hr ) -  212.9 MB"
    },
    {
      "id": "tt2261287",
      "type": "movie",
      "name": "Ballerina I Viktor ( H i S ) -  688.8 MB"
    },
    {
      "id": "tt0112453",
      "type": "movie",
      "name": "Balto 01 ( H i S ) -  855.7 MB"
    },
    {
      "id": "tt0281634",
      "type": "movie",
      "name": "Balto 02 ( H i S ) -  594.5 MB"
    },
    {
      "id": "tt0423849",
      "type": "movie",
      "name": "Balto 03 ( H i S ) -  652.5 MB"
    },
    {
      "id": "tt0034492",
      "type": "movie",
      "name": "Bambi 01 ( H i S ) -  524.8 MB"
    },
    {
      "id": "tt0447854",
      "type": "movie",
      "name": "Bambi 02 ( Hr ) -  379.2 MB"
    },
    {
      "id": "tt0062708",
      "type": "movie",
      "name": "Bandolero ( Sr ) -  796.5 MB"
    },
    {
      "id": "tt8435268",
      "type": "movie",
      "name": "Bas Super ( Sr ) -  477.8 MB"
    },
    {
      "id": "tt0143127",
      "type": "movie",
      "name": "Batman I Mr Freeze Subzero ( Hr ) -  456.2 MB"
    },
    {
      "id": "tt21197740",
      "type": "movie",
      "name": "Batman I Supermen ( Hr ) -  372.4 MB"
    },
    {
      "id": "tt0389790",
      "type": "movie",
      "name": "Bee Movie ( Hr ) -  743.8 MB"
    },
    {
      "id": "tt0243657",
      "type": "movie",
      "name": "Beli Ocnjak ( Sr ) -  417.5 MB"
    },
    {
      "id": "tt0286244",
      "type": "movie",
      "name": "Belvil Randevu ( Np ) -  569.6 MB"
    },
    {
      "id": "tt14422108",
      "type": "movie",
      "name": "Ben 10 Alien X Tinction ( H i S ) -  333.8 MB"
    },
    {
      "id": "tt14317168",
      "type": "movie",
      "name": "Ben 10 Ben 10010 ( H i S ) -  343.8 MB"
    },
    {
      "id": "tt14422106",
      "type": "movie",
      "name": "Ben 10 Ben Gen 10 ( H  S ) -  413.1 MB"
    },
    {
      "id": "tt0052618",
      "type": "movie",
      "name": "Ben Hur ( Sr ) -  527.0 MB"
    },
    {
      "id": "tt0444200",
      "type": "movie",
      "name": "Ben I Ja ( Sr ) -  142.1 MB"
    },
    {
      "id": "tt1799516",
      "type": "movie",
      "name": "Benji ( Hr ) -  659.1 MB"
    },
    {
      "id": "tt2245084",
      "type": "movie",
      "name": "Big Hero 6 ( H I S ) -  832.7 MB"
    },
    {
      "id": "tt2163203",
      "type": "movie",
      "name": "Big Time Movie ( H i S ) -  639.7 MB"
    },
    {
      "id": "tt6922062",
      "type": "movie",
      "name": "Binti ( Sr ) -  729.9 MB"
    },
    {
      "id": "tt0089421",
      "type": "movie",
      "name": "Blago Kralja Solomona ( Hr ) -  337.4 MB"
    },
    {
      "id": "tt6948600",
      "type": "movie",
      "name": "Blurt ( Hr ) -  364.9 MB"
    },
    {
      "id": "tt1855134",
      "type": "movie",
      "name": "Bozicna Avantura ( Hr ) -  288.1 MB"
    },
    {
      "id": "tt39333490",
      "type": "movie",
      "name": "Bozicna Bajka ( Hr ) -  252.2 MB"
    },
    {
      "id": "tt0104940",
      "type": "movie",
      "name": "Bozicna Prica ( Hr ) -  216.3 MB"
    },
    {
      "id": "tt3473654",
      "type": "movie",
      "name": "Bozicna Vila ( Hr ) -  299.3 MB"
    },
    {
      "id": "tt24852126",
      "type": "movie",
      "name": "Bozicni Rap ( Hr ) -  135.0 MB"
    },
    {
      "id": "tt14187584",
      "type": "movie",
      "name": "Bozicno Drvce ( Hr ) -  195.9 MB"
    },
    {
      "id": "tt0064037",
      "type": "movie",
      "name": "Bozicno Drvo ( H i S ) -  436.0 MB"
    },
    {
      "id": "tt3251832",
      "type": "movie",
      "name": "Bratz Genie Magic ( H i S ) -  630.2 MB"
    },
    {
      "id": "tt5770430",
      "type": "movie",
      "name": "Brzi Ozi ( Hr ) -  619.8 MB"
    },
    {
      "id": "tt21195548",
      "type": "movie",
      "name": "Buba ( Np ) -  740.7 MB"
    },
    {
      "id": "tt0061439",
      "type": "movie",
      "name": "Camelot ( H I S ).mp4 -  581.4 MB"
    },
    {
      "id": "tt1180335",
      "type": "movie",
      "name": "Carobna Kocka ( Hr ).mp4 -  319.9 MB"
    },
    {
      "id": "tt4144206",
      "type": "movie",
      "name": "Carobni Mac ( H i S ).mp4 -  969.2 MB"
    },
    {
      "id": "tt17164334",
      "type": "movie",
      "name": "Carobni Princ ( H i S ).mp4 -  632.3 MB"
    },
    {
      "id": "tt7892450",
      "type": "movie",
      "name": "Carobni Prolaz ( Hr ).mp4 -  820.1 MB"
    },
    {
      "id": "tt0339334",
      "type": "movie",
      "name": "Carobni Vrtuljak ( H I S ).mp4 -  762.0 MB"
    },
    {
      "id": "tt0333215",
      "type": "movie",
      "name": "Carobnjakov Sesir ( Hr ).mp4 -  874.1 MB"
    },
    {
      "id": "tt5954304",
      "type": "movie",
      "name": "Carolija Usnulog Zmaja ( H i S ).mp4 -  1.1 GB"
    },
    {
      "id": "tt1535430",
      "type": "movie",
      "name": "Cheburashka ( Hr ).mp4 -  400.5 MB"
    },
    {
      "id": "tt14923260",
      "type": "movie",
      "name": "Chupa ( Hr ).mp4 -  719.8 MB"
    },
    {
      "id": "tt1235837",
      "type": "movie",
      "name": "Cica Mica Nesretna Je Prica 01 ( Hr ).mp4 -  513.5 MB"
    },
    {
      "id": "tt1235837",
      "type": "movie",
      "name": "Cica Mica Nesretna Je Prica 02 ( H I S ).mp4 -  579.1 MB"
    },
    {
      "id": "tt2380307",
      "type": "movie",
      "name": "Coco ( H i S ).mp4 -  1.0 GB"
    },
    {
      "id": "tt10954718",
      "type": "movie",
      "name": "Covpas ( H I S ).mp4 -  802.7 MB"
    },
    {
      "id": "tt0088814",
      "type": "movie",
      "name": "Crni Kazan ( Sr ).mp4 -  463.1 MB"
    },
    {
      "id": "tt8097030",
      "type": "movie",
      "name": "Crvena Panda ( H i S ).mp4 -  869.3 MB"
    },
    {
      "id": "tt4429160",
      "type": "movie",
      "name": "Crvencipelica I 7 Patuljaka ( H i S ).mp4 -  721.9 MB"
    },
    {
      "id": "tt2572216",
      "type": "movie",
      "name": "Crvene Cipelice ( Hr ).mp4 -  399.1 MB"
    },
    {
      "id": "tt38271902",
      "type": "movie",
      "name": "Crvenkapa ( H I S ).mp4 -  347.2 MB"
    },
    {
      "id": "tt0374589",
      "type": "movie",
      "name": "Crvenkapica ( Hr ).mp4 -  219.9 MB"
    },
    {
      "id": "tt0268282",
      "type": "movie",
      "name": "Cudesna Suma ( Hr ).mp4 -  1.2 GB"
    },
    {
      "id": "tt0133930",
      "type": "movie",
      "name": "Cudnovate Zgode Segrta Hlapica ( Hr ).mp4 -  684.5 MB"
    },
    {
      "id": "tt2299368",
      "type": "movie",
      "name": "Cudnovili Bozic ( H i S ).mp4 -  729.2 MB"
    },
    {
      "id": "tt0198781",
      "type": "movie",
      "name": "Cudovista Iz Ormara ( H i S ).mp4 -  893.1 MB"
    },
    {
      "id": "tt0892782",
      "type": "movie",
      "name": "Cudovista Protiv Vanzemaljaca ( Hr ).mp4 -  733.0 MB"
    },
    {
      "id": "tt1453405",
      "type": "movie",
      "name": "Cudovista Sa Sveucilista ( Hr ).mp4 -  831.3 MB"
    },
    {
      "id": "tt1314248",
      "type": "movie",
      "name": "Cudoviste Iz Mora ( Hr ).mp4 -  988.9 MB"
    },
    {
      "id": "tt37677952",
      "type": "movie",
      "name": "Culjci ( Hr ).mp4 -  486.4 MB"
    },
    {
      "id": "tt4581522",
      "type": "movie",
      "name": "Cvrcak I Mrav ( Predstava ) ( Hr ).mp4 -  106.7 MB"
    },
    {
      "id": "tt4581522",
      "type": "movie",
      "name": "Cvrcak I Mravica ( Hr ).mp4 -  584.4 MB"
    },
    {
      "id": "tt0387954",
      "type": "movie",
      "name": "Cvrcak Na Ognjistu ( Hr ).mp4 -  283.4 MB"
    },
    {
      "id": "tt12672536",
      "type": "movie",
      "name": "D Artanjan ( Hr ).mp4 -  680.9 MB"
    },
    {
      "id": "tt12672536",
      "type": "movie",
      "name": "D Artanjan ( Sr ).mp4 -  550.0 MB"
    },
    {
      "id": "tt13379830",
      "type": "movie",
      "name": "Dambo ( Sr ).mp4 -  534.7 MB"
    },
    {
      "id": "tt3861390",
      "type": "movie",
      "name": "Dambo 2019 ( H i S ).mp4 -  869.5 MB"
    },
    {
      "id": "tt7821192",
      "type": "movie",
      "name": "Dan Za Da ( Hr ).mp4 -  816.3 MB"
    },
    {
      "id": "tt8912936",
      "type": "movie",
      "name": "Dc Liga Super Ljubimaca ( H i S ).mp4 -  803.6 MB"
    },
    {
      "id": "tt7018010",
      "type": "movie",
      "name": "Deda Mraz i Kompanija ( Sr ).mp4 -  698.5 MB"
    },
    {
      "id": "tt7549618",
      "type": "movie",
      "name": "Delfin Berni ( Sr ).mp4 -  737.9 MB"
    },
    {
      "id": "tt1814643",
      "type": "movie",
      "name": "Despicable Me 01 ( Hr ).mp4 -  655.3 MB"
    },
    {
      "id": "tt1690953",
      "type": "movie",
      "name": "Despicable Me 02 ( H i S ).mp4 -  873.6 MB"
    },
    {
      "id": "tt3469046",
      "type": "movie",
      "name": "Despicable Me 03 ( H I S ).mp4 -  831.4 MB"
    },
    {
      "id": "tt7510222",
      "type": "movie",
      "name": "Despicable Me 04 ( H I S ).mp4 -  737.3 MB"
    },
    {
      "id": "tt10691126",
      "type": "movie",
      "name": "Dia Of The Dead ( Hr ).mp4 -  746.0 MB"
    },
    {
      "id": "tt14162824",
      "type": "movie",
      "name": "Dinosaurus ( Sr ).mp4 -  624.8 MB"
    },
    {
      "id": "tt0372238",
      "type": "movie",
      "name": "Dinotopija Potraga Za Starim Rubinom ( Hr ).mp4 -  512.3 MB"
    },
    {
      "id": "tt29623480",
      "type": "movie",
      "name": "Divlji Robot ( H I S ).mp4 -  1.2 GB"
    },
    {
      "id": "tt11084896",
      "type": "movie",
      "name": "Divlji Spirit ( Hr ).mp4 -  688.8 MB"
    },
    {
      "id": "tt0423294",
      "type": "movie",
      "name": "Divlji Talasi ( Hr ).mp4 -  816.7 MB"
    },
    {
      "id": "tt8716800",
      "type": "movie",
      "name": "DJ Cinderella ( Hr ).mp4 -  813.9 MB"
    },
    {
      "id": "tt27190968",
      "type": "movie",
      "name": "Dnevnik Pauline P ( Hr ).mp4 -  931.6 MB"
    },
    {
      "id": "tt1979388",
      "type": "movie",
      "name": "Dobri Dinosaur ( H i S ).mp4 -  1.2 GB"
    },
    {
      "id": "tt14592064",
      "type": "movie",
      "name": "Domaca Ekipa ( Hr ).mp4 -  826.7 MB"
    },
    {
      "id": "tt0374623",
      "type": "movie",
      "name": "Don Kihot ( Hr ).mp4 -  525.1 MB"
    },
    {
      "id": "tt32621553",
      "type": "movie",
      "name": "Dora U Potrazi Za Sol Doradom ( Sr ).mp4 -  846.3 MB"
    },
    {
      "id": "tt0425960",
      "type": "movie",
      "name": "Dragons Fire  Ice ( Hr ).mp4 -  765.0 MB"
    },
    {
      "id": "tt21040884",
      "type": "movie",
      "name": "Drugari ( Sr ).mp4 -  851.9 MB"
    },
    {
      "id": "tt1918789",
      "type": "movie",
      "name": "Duga ( Hr ).mp4 -  425.6 MB"
    },
    {
      "id": "tt4701724",
      "type": "movie",
      "name": "Dugi Iz Kamenog Doba ( H i S ).mp4 -  802.4 MB"
    },
    {
      "id": "tt1946445",
      "type": "movie",
      "name": "Duh Babe Ilonke ( Hr ).mp4 -  535.1 MB"
    },
    {
      "id": "tt0776770",
      "type": "movie",
      "name": "Duh U Mocvari ( Hr ).mp4 -  668.4 MB"
    },
    {
      "id": "tt0315000",
      "type": "movie",
      "name": "El Cid ( Hr ) -  301.6 MB"
    },
    {
      "id": "tt7877982",
      "type": "movie",
      "name": "Eldorado ( Hr ) -  187.4 MB"
    },
    {
      "id": "tt4900148",
      "type": "movie",
      "name": "ELIO ( Sr ).mp4 -  566.8 MB"
    },
    {
      "id": "tt2853794",
      "type": "movie",
      "name": "Eliot ( Sr ) -  498.2 MB"
    },
    {
      "id": "tt4177856",
      "type": "movie",
      "name": "Eliot Spasava Bozic ( H i S ) -  769.7 MB"
    },
    {
      "id": "tt2953050",
      "type": "movie",
      "name": "Enkanto Carobni Svet ( H i S ) -  984.4 MB"
    },
    {
      "id": "tt17162512",
      "type": "movie",
      "name": "Eraksi ( Hr ) -  72.1 MB"
    },
    {
      "id": "tt1816518",
      "type": "movie",
      "name": "Ernest I Celestina ( H I S ) -  437.6 MB"
    },
    {
      "id": "tt6324278",
      "type": "movie",
      "name": "Everest Mladi Jeti ( Hr ) -  772.3 MB"
    },
    {
      "id": "tt4685636",
      "type": "movie",
      "name": "Fantasticno Putovanje U Oz ( Sr ) -  746.1 MB"
    },
    {
      "id": "tt3411444",
      "type": "movie",
      "name": "Ferdinand ( H I S ) -  871.1 MB"
    },
    {
      "id": "tt22774688",
      "type": "movie",
      "name": "Film O Nogometu ( Hr ) -  544.0 MB"
    },
    {
      "id": "tt32597616",
      "type": "movie",
      "name": "Frka ( H i S ) -  694.0 MB"
    },
    {
      "id": "tt32214143",
      "type": "movie",
      "name": "Gabina Kuca Lutaka Film ( Hr ).mp4 -  1.0 GB"
    },
    {
      "id": "tt8823390",
      "type": "movie",
      "name": "Ganesa 02 ( Sr ).mp4 -  296.7 MB"
    },
    {
      "id": "tt0377981",
      "type": "movie",
      "name": "Gnomeo I Julija ( H I S ).mp4 -  713.3 MB"
    },
    {
      "id": "tt6348138",
      "type": "movie",
      "name": "Gospodin Link ( H i S ).mp4 -  569.0 MB"
    },
    {
      "id": "tt5095510",
      "type": "movie",
      "name": "Granimir ( Hr ).mp4 -  169.7 MB"
    },
    {
      "id": "tt2709692",
      "type": "movie",
      "name": "Grinch 2018 ( H i S ).mp4 -  823.5 MB"
    },
    {
      "id": "tt26446278",
      "type": "movie",
      "name": "Grof Monte Kristo ( Sr ).mp4 -  306.5 MB"
    },
    {
      "id": "tt27114092",
      "type": "movie",
      "name": "Grom ( Hr ).mp4 -  407.8 MB"
    },
    {
      "id": "tt1461418",
      "type": "movie",
      "name": "Grubzon ( Hr ).mp4 -  121.4 MB"
    },
    {
      "id": "tt0031397",
      "type": "movie",
      "name": "Guliverova Putovanja ( Dizni H I S ).mp4 -  745.7 MB"
    },
    {
      "id": "tt0031397",
      "type": "movie",
      "name": "Guliverova Putovanja ( Kiosk ) ( Hr ).mp4 -  248.2 MB"
    },
    {
      "id": "tt0366548",
      "type": "movie",
      "name": "Happy Feet 01 ( Hr ).mp4 -  721.2 MB"
    },
    {
      "id": "tt4984690",
      "type": "movie",
      "name": "Herkules (1997).mp4 -  782.7 MB"
    },
    {
      "id": "tt0314166",
      "type": "movie",
      "name": "Hey Arnold ( H i S ).mp4 -  592.9 MB"
    },
    {
      "id": "tt13176330",
      "type": "movie",
      "name": "Hitpig ( H i S ).mp4 -  614.9 MB"
    },
    {
      "id": "tt1411704",
      "type": "movie",
      "name": "Hop ( Hr ).mp4 -  583.7 MB"
    },
    {
      "id": "tt0451079",
      "type": "movie",
      "name": "Horton ( H I S ).mp4 -  519.0 MB"
    },
    {
      "id": "tt2510894",
      "type": "movie",
      "name": "Hotel Transilvanija 02 ( H i S ).mp4 -  666.5 MB"
    },
    {
      "id": "tt5220122",
      "type": "movie",
      "name": "Hotel Transilvanija 03 ( H i S ).mp4 -  795.1 MB"
    },
    {
      "id": "tt9848626",
      "type": "movie",
      "name": "Hotel Transilvanija 04 ( H i S ).mp4 -  808.8 MB"
    },
    {
      "id": "tt1217209",
      "type": "movie",
      "name": "Hrabra Merida ( H I S ).mp4 -  564.1 MB"
    },
    {
      "id": "tt0092695",
      "type": "movie",
      "name": "Hrabri Mali Toster ( Hr ).mp4 -  589.9 MB"
    },
    {
      "id": "tt4643580",
      "type": "movie",
      "name": "Hrabri Petao ( H i S ).mp4 -  715.1 MB"
    },
    {
      "id": "tt0064452",
      "type": "movie",
      "name": "Hua Mulan ( Sr ).mp4 -  472.4 MB"
    },
    {
      "id": "tt3711622",
      "type": "movie",
      "name": "Hugo I Lovci Na Duhove ( Hr ).mp4 -  723.6 MB"
    },
    {
      "id": "tt1325753",
      "type": "movie",
      "name": "Hulk Protiv Tora ( Hr ).mp4 -  417.3 MB"
    },
    {
      "id": "tt0451769",
      "type": "movie",
      "name": "Imaginum ( Sr ) -  332.1 MB"
    },
    {
      "id": "tt6661616",
      "type": "movie",
      "name": "Inspektor Brk ( Hr ) -  784.5 MB"
    },
    {
      "id": "tt0093144",
      "type": "movie",
      "name": "Ivica i Marica ( Hr ) -  242.5 MB"
    },
    {
      "id": "tt13926132",
      "type": "movie",
      "name": "Ivy I Bean 01 ( Hr ) -  316.6 MB"
    },
    {
      "id": "tt0317705",
      "type": "movie",
      "name": "Izbavitelji 01 ( Hr ) -  898.4 MB"
    },
    {
      "id": "tt3606756",
      "type": "movie",
      "name": "Izbavitelji 02 ( H i S ) -  1011.4 MB"
    },
    {
      "id": "tt11152168",
      "type": "movie",
      "name": "Izmisljeni Prijatelji ( H i S ) -  843.6 MB"
    },
    {
      "id": "tt0084837",
      "type": "movie",
      "name": "Izumitelj ( Sr ) -  507.6 MB"
    },
    {
      "id": "tt22022452",
      "type": "movie",
      "name": "Izvrnuto Obrnuto 02 ( H i S ) -  923.8 MB"
    },
    {
      "id": "tt7080422",
      "type": "movie",
      "name": "Jahac Zmaja ( H i S ).mp4 -  753.7 MB"
    },
    {
      "id": "tt2934844",
      "type": "movie",
      "name": "Jinxed ( Hr ).mp4 -  664.2 MB"
    },
    {
      "id": "tt1639826",
      "type": "movie",
      "name": "Juraj I Hrabri Vitezovi ( H I S ).mp4 -  836.9 MB"
    },
    {
      "id": "tt0170016",
      "type": "movie",
      "name": "Kako Je Grinch Ukrao Bozic ( Hr ) -  163.4 MB"
    },
    {
      "id": "tt8048384",
      "type": "movie",
      "name": "Kapetan Sabljozubi I Magicni Dijamant ( H i S ) -  708.3 MB"
    },
    {
      "id": "tt7478452",
      "type": "movie",
      "name": "Kavalan ( Sr ) -  402.4 MB"
    },
    {
      "id": "tt1487931",
      "type": "movie",
      "name": "Khumba ( H I S ) -  495.6 MB"
    },
    {
      "id": "tt7050476",
      "type": "movie",
      "name": "Kikoriki Deja Vu ( Sr ) -  762.4 MB"
    },
    {
      "id": "tt0116583",
      "type": "movie",
      "name": "Kiriku 01 ( Sr ) -  330.3 MB"
    },
    {
      "id": "tt0455142",
      "type": "movie",
      "name": "Kiriku 02 ( Sr ) -  285.7 MB"
    },
    {
      "id": "tt4729430",
      "type": "movie",
      "name": "Klaus ( Hr ) -  348.4 MB"
    },
    {
      "id": "tt0283426",
      "type": "movie",
      "name": "Knjiga O Dzungli 02 ( H i S ) -  631.2 MB"
    },
    {
      "id": "tt14562756",
      "type": "movie",
      "name": "Kod Kuce ( H I S ) -  707.0 MB"
    },
    {
      "id": "tt1587420",
      "type": "movie",
      "name": "Kompilacija ( Hr ) -  1.1 GB"
    },
    {
      "id": "tt4494382",
      "type": "movie",
      "name": "Kondorito ( Sr ) -  411.6 MB"
    },
    {
      "id": "tt1620449",
      "type": "movie",
      "name": "Konferencija Zivotinja ( H i S ) -  689.0 MB"
    },
    {
      "id": "tt6563576",
      "type": "movie",
      "name": "Korgi Kraljevski Pas Velikog Srca ( H I S ) -  505.5 MB"
    },
    {
      "id": "tt1086798",
      "type": "movie",
      "name": "Kornjaca I Zec ( 2012 ) ( Hr ) -  366.9 MB"
    },
    {
      "id": "tt14205554",
      "type": "movie",
      "name": "KPop Demon Hunters ( Hr ) -  665.2 MB"
    },
    {
      "id": "tt2619806",
      "type": "movie",
      "name": "Kralj I Ja ( Sr ) -  448.4 MB"
    },
    {
      "id": "tt0079820",
      "type": "movie",
      "name": "Kralj I Ptica ( Sr ) -  510.9 MB"
    },
    {
      "id": "tt0110357",
      "type": "movie",
      "name": "Kralj Lavova ( 2019 H i S ) -  889.3 MB"
    },
    {
      "id": "tt8637498",
      "type": "movie",
      "name": "Kralj Majmuna ( Hr ) -  855.1 MB"
    },
    {
      "id": "tt7967302",
      "type": "movie",
      "name": "Kralj Nad Kraljevima ( Hr ) -  1.0 GB"
    },
    {
      "id": "tt1836776",
      "type": "movie",
      "name": "Kraljevic I Prosjak ( H I S ) -  254.1 MB"
    },
    {
      "id": "tt0288441",
      "type": "movie",
      "name": "Krcko Orascic ( H i S ) -  363.5 MB"
    },
    {
      "id": "tt0481499",
      "type": "movie",
      "name": "Krudovi 01 ( H I S ) -  846.6 MB"
    },
    {
      "id": "tt2850386",
      "type": "movie",
      "name": "Krudovi 02 ( H i S ) -  768.5 MB"
    },
    {
      "id": "tt11276598",
      "type": "movie",
      "name": "Kucni Ljubimci Na Tajnom Zadatku ( H i S ) -  804.5 MB"
    },
    {
      "id": "tt1302011",
      "type": "movie",
      "name": "Kung Fu Panda 02 ( H I S ) -  814.2 MB"
    },
    {
      "id": "tt2267968",
      "type": "movie",
      "name": "Kung Fu Panda 03 ( H I S ) -  988.8 MB"
    },
    {
      "id": "tt21692408",
      "type": "movie",
      "name": "Kung Fu Panda 04 ( H I S ) -  853.3 MB"
    },
    {
      "id": "tt0059039",
      "type": "movie",
      "name": "Lav Leon ( Hr ).mp4 -  223.0 MB"
    },
    {
      "id": "tt10923940",
      "type": "movie",
      "name": "Lava ( H i S ).mp4 -  38.8 MB"
    },
    {
      "id": "tt13321782",
      "type": "movie",
      "name": "Le Piaf ( Np ).mp4 -  160.5 MB"
    },
    {
      "id": "tt0438097",
      "type": "movie",
      "name": "Ledeno Doba 02 ( H I S ).mp4 -  520.1 MB"
    },
    {
      "id": "tt1080016",
      "type": "movie",
      "name": "Ledeno Doba 03 ( H I S ).mp4 -  617.4 MB"
    },
    {
      "id": "tt1667889",
      "type": "movie",
      "name": "Ledeno Doba 04 ( H I S ).mp4 -  627.1 MB"
    },
    {
      "id": "tt3416828",
      "type": "movie",
      "name": "Ledeno Doba 05 ( H I S ).mp4 -  716.1 MB"
    },
    {
      "id": "tt0120762",
      "type": "movie",
      "name": "Legenda O Mulan ( Hr ).mp4 -  231.3 MB"
    },
    {
      "id": "tt0120762",
      "type": "movie",
      "name": "Legenda O Mulan ( Sr ).mp4 -  186.4 MB"
    },
    {
      "id": "tt2296935",
      "type": "movie",
      "name": "Legenda O Sarili ( H i S ).mp4 -  474.5 MB"
    },
    {
      "id": "tt5333842",
      "type": "movie",
      "name": "Legende Skrivenog Hrama ( Hr ).mp4 -  558.5 MB"
    },
    {
      "id": "tt5333842",
      "type": "movie",
      "name": "Legende Skrivenog Hrama ( Sr ).mp4 -  555.2 MB"
    },
    {
      "id": "tt4116284",
      "type": "movie",
      "name": "Lego Betmen ( Hr ).mp4 -  726.1 MB"
    },
    {
      "id": "tt3513498",
      "type": "movie",
      "name": "Lego Film 02 ( Hr ).mp4 -  413.7 MB"
    },
    {
      "id": "tt0202452",
      "type": "movie",
      "name": "Leif Ericson ( Hr ).mp4 -  522.2 MB"
    },
    {
      "id": "tt5755238",
      "type": "movie",
      "name": "Leo ( Hr ).mp4 -  686.4 MB"
    },
    {
      "id": "tt7139246",
      "type": "movie",
      "name": "Leo Da Vinci Misija Mona Liza ( H i S ).mp4 -  743.4 MB"
    },
    {
      "id": "tt1086293",
      "type": "movie",
      "name": "Lesi 2005 ( Hr ).mp4 -  916.4 MB"
    },
    {
      "id": "tt2371287",
      "type": "movie",
      "name": "Letni Kamp ( Hr ).mp4 -  956.1 MB"
    },
    {
      "id": "tt14668630",
      "type": "movie",
      "name": "Lil Lil Krokodil ( H i S ).mp4 -  731.8 MB"
    },
    {
      "id": "tt0486761",
      "type": "movie",
      "name": "Lilo I Stic Film ( Sr ).mp4 -  487.9 MB"
    },
    {
      "id": "tt0082406",
      "type": "movie",
      "name": "Lisica I Pas ( Sr ).mp4 -  475.6 MB"
    },
    {
      "id": "tt21232992",
      "type": "movie",
      "name": "Ljetni Kamp ( Hr ).mp4 -  971.9 MB"
    },
    {
      "id": "tt4500214",
      "type": "movie",
      "name": "Lola I Velika Tajna (Hr).mp4 -  747.2 MB"
    },
    {
      "id": "tt1482459",
      "type": "movie",
      "name": "Lorax Zastitnik Sume ( Hr ).mp4 -  516.6 MB"
    },
    {
      "id": "tt30017619",
      "type": "movie",
      "name": "Losi Momci ( H i S ).mp4 -  851.4 MB"
    },
    {
      "id": "tt33130902",
      "type": "movie",
      "name": "Losi Momci Ukleta Pljacka ( Hr ).mp4 -  97.7 MB"
    },
    {
      "id": "tt2080337",
      "type": "movie",
      "name": "Lote I Tajna Mesecevog Kamena ( H i S ).mp4 -  591.1 MB"
    },
    {
      "id": "tt4058572",
      "type": "movie",
      "name": "Ludo Krstarenje ( Hr ).mp4 -  654.0 MB"
    },
    {
      "id": "tt4410000",
      "type": "movie",
      "name": "Luis I Drustvo Iz Svemira ( H i S ).mp4 -  696.2 MB"
    },
    {
      "id": "tt0115254",
      "type": "movie",
      "name": "Luka ( H I S ).mp4 -  895.3 MB"
    },
    {
      "id": "tt6489160",
      "type": "movie",
      "name": "Luka I Carobni Muzej ( Hr ).mp4 -  507.9 MB"
    },
    {
      "id": "tt0057546",
      "type": "movie",
      "name": "Mac U Kamenu ( Sr ) -  582.7 MB"
    },
    {
      "id": "tt0439567",
      "type": "movie",
      "name": "Macak Feliks Spasava Bozic ( H I S ) -  641.9 MB"
    },
    {
      "id": "tt3915174",
      "type": "movie",
      "name": "Macak U Cizmama ( 2012 ) ( H I S ) -  746.6 MB"
    },
    {
      "id": "tt3915174",
      "type": "movie",
      "name": "Macak U Cizmama ( Hr ) -  293.9 MB"
    },
    {
      "id": "tt3915174",
      "type": "movie",
      "name": "Macak U Cizmama ( Tv ) ( Hr ) -  434.2 MB"
    },
    {
      "id": "tt3915174",
      "type": "movie",
      "name": "Macak U Cizmama Poslednja Zelja ( H i S ) -  1.2 GB"
    },
    {
      "id": "tt0065421",
      "type": "movie",
      "name": "Macke Iz Visokog Drustva ( Sr ) -  478.5 MB"
    },
    {
      "id": "tt0438405",
      "type": "movie",
      "name": "Madagaskar 01 ( Hr ) -  661.7 MB"
    },
    {
      "id": "tt0479952",
      "type": "movie",
      "name": "Madagaskar 02 ( H I S ) -  767.5 MB"
    },
    {
      "id": "tt1277953",
      "type": "movie",
      "name": "Madagaskar 03 ( H I S ) -  922.4 MB"
    },
    {
      "id": "tt1526300",
      "type": "movie",
      "name": "Madagaskar Bozic ( Hr ) -  210.2 MB"
    },
    {
      "id": "tt0159251",
      "type": "movie",
      "name": "Madelina ( H i S ) -  461.2 MB"
    },
    {
      "id": "tt0186311",
      "type": "movie",
      "name": "Mala Lokomotiva ( Hr ) -  232.3 MB"
    },
    {
      "id": "tt0097757",
      "type": "movie",
      "name": "Mala Sirena 01 ( H i S ) -  778.2 MB"
    },
    {
      "id": "tt5493944",
      "type": "movie",
      "name": "Mala Sirena 02 ( Sr ) -  490.3 MB"
    },
    {
      "id": "tt1576423",
      "type": "movie",
      "name": "Mala Velika Panda ( H i S ) -  542.0 MB"
    },
    {
      "id": "tt29258548",
      "type": "movie",
      "name": "Male Sape Na Velikom Putovanju ( Sr ) -  619.9 MB"
    },
    {
      "id": "tt13387818",
      "type": "movie",
      "name": "Mali Alan ( Sr ) -  473.4 MB"
    },
    {
      "id": "tt5715410",
      "type": "movie",
      "name": "Mali Bigfoot ( H i S ) -  653.9 MB"
    },
    {
      "id": "tt8241000",
      "type": "movie",
      "name": "Malci Otpisanci ( Hr ) -  578.3 MB"
    },
    {
      "id": "tt8241000",
      "type": "movie",
      "name": "Malci Otpisanci ( Sr ) -  585.5 MB"
    },
    {
      "id": "tt5053088",
      "type": "movie",
      "name": "Mali Princ ( H I S ) -  627.2 MB"
    },
    {
      "id": "tt3874544",
      "type": "movie",
      "name": "Mali Sef 01 ( H I S ) -  640.3 MB"
    },
    {
      "id": "tt6932874",
      "type": "movie",
      "name": "Mali Sef 02 ( H i S ) -  1.1 GB"
    },
    {
      "id": "tt23546646",
      "type": "movie",
      "name": "Mali Sef Bozic ( Hr ) -  262.1 MB"
    },
    {
      "id": "tt23546646",
      "type": "movie",
      "name": "Mali Sef Bozic ( Sr ) -  317.2 MB"
    },
    {
      "id": "tt1614955",
      "type": "movie",
      "name": "Marko Makako ( Sr ) -  540.0 MB"
    },
    {
      "id": "tt2985984",
      "type": "movie",
      "name": "Marta I Bozicno Cudoviste ( Hr ) -  104.9 MB"
    },
    {
      "id": "tt0117008",
      "type": "movie",
      "name": "Matilda ( Hr ) -  1.1 GB"
    },
    {
      "id": "tt0076381",
      "type": "movie",
      "name": "Mecava ( Hr ) -  732.3 MB"
    },
    {
      "id": "tt21054736",
      "type": "movie",
      "name": "Medino Bozicno Cudo ( Hr ) -  537.2 MB"
    },
    {
      "id": "tt1449283",
      "type": "movie",
      "name": "Medvjedic Winnie ( Hr ) -  298.6 MB"
    },
    {
      "id": "tt1001526",
      "type": "movie",
      "name": "Megaum ( Hr ) -  601.0 MB"
    },
    {
      "id": "tt0792978",
      "type": "movie",
      "name": "Mia I Migu ( Sr ) -  371.4 MB"
    },
    {
      "id": "tt23546638",
      "type": "movie",
      "name": "Mighty Express Utrka Mocnih Vlakova ( Hr ) -  257.8 MB"
    },
    {
      "id": "tt0085936",
      "type": "movie",
      "name": "Mikijeva Bozicna Prica ( Sr ) -  199.0 MB"
    },
    {
      "id": "tt3566834",
      "type": "movie",
      "name": "Minecraft Film ( H i S ) -  1.1 GB"
    },
    {
      "id": "tt10600398",
      "type": "movie",
      "name": "Mini Heroji ( Hr ) -  1.0 GB"
    },
    {
      "id": "tt22184976",
      "type": "movie",
      "name": "Minions 01 ( H I S ) -  608.5 MB"
    },
    {
      "id": "tt23382644",
      "type": "movie",
      "name": "Minions 02 ( H I S ) -  958.1 MB"
    },
    {
      "id": "tt7296782",
      "type": "movie",
      "name": "Minuscule 02 ( Np ) -  364.3 MB"
    },
    {
      "id": "tt0181175",
      "type": "movie",
      "name": "Mlada Pocahontas ( Hr ) -  251.5 MB"
    },
    {
      "id": "tt0489210",
      "type": "movie",
      "name": "Mladi Herkules ( Hr ) -  193.2 MB"
    },
    {
      "id": "tt7662644",
      "type": "movie",
      "name": "Moj Dida Je Pao S Marsa ( Hr ) -  576.1 MB"
    },
    {
      "id": "tt8734822",
      "type": "movie",
      "name": "Moj Mali Poni Najbolji Poklon Svih Vremena ( Sr ) -  270.9 MB"
    },
    {
      "id": "tt4131800",
      "type": "movie",
      "name": "Moj Mali Pony Film 2017 ( H i S ) -  692.3 MB"
    },
    {
      "id": "tt0096283",
      "type": "movie",
      "name": "Moj Susjed Totoro ( Sr ) -  375.4 MB"
    },
    {
      "id": "tt15096796",
      "type": "movie",
      "name": "Moja Cudovisna Obitelj 02 ( H i S ) -  1.2 GB"
    },
    {
      "id": "tt6556552",
      "type": "movie",
      "name": "Momo ( Sr )  -  451.3 MB"
    },
    {
      "id": "tt8337158",
      "type": "movie",
      "name": "Monstermania ( H i S ) -  1.1 GB"
    },
    {
      "id": "tt9288046",
      "type": "movie",
      "name": "Morska Neman ( Hr ) -  1018.5 MB"
    },
    {
      "id": "tt0188916",
      "type": "movie",
      "name": "Mrav Pesadinac ( Sr ) -  571.2 MB"
    },
    {
      "id": "tt4581522",
      "type": "movie",
      "name": "Mravi ( Hr ) -  373.9 MB"
    },
    {
      "id": "tt5221354",
      "type": "movie",
      "name": "Mulan 01 ( Sr ) -  443.4 MB"
    },
    {
      "id": "tt33059650",
      "type": "movie",
      "name": "Mulan 02 ( Sr ) -  431.6 MB"
    },
    {
      "id": "tt1869724",
      "type": "movie",
      "name": "Najmanji Andeo ( Hr ) -  324.0 MB"
    },
    {
      "id": "tt36932684",
      "type": "movie",
      "name": "Napred ( H i S ) -  865.5 MB"
    },
    {
      "id": "tt0988982",
      "type": "movie",
      "name": "Naruto Shippuden ( Sr ) -  547.5 MB"
    },
    {
      "id": "tt5125894",
      "type": "movie",
      "name": "Navijacice ( Sr ) -  523.9 MB"
    },
    {
      "id": "tt11286314",
      "type": "movie",
      "name": "Ne Gledaj Gore ( Hr ) -  1.6 GB"
    },
    {
      "id": "tt11034276",
      "type": "movie",
      "name": "Nebesa ( Hr ) -  461.0 MB"
    },
    {
      "id": "tt20221460",
      "type": "movie",
      "name": "Nerazdvojni ( Sr ) -  728.2 MB"
    },
    {
      "id": "tt7504818",
      "type": "movie",
      "name": "Nesavrseni Robot Ron ( H i S ) -  974.9 MB"
    },
    {
      "id": "tt2353868",
      "type": "movie",
      "name": "Neslomljivi Duh ( Hr ) -  914.6 MB"
    },
    {
      "id": "tt0024184",
      "type": "movie",
      "name": "Nevidljivi Covek ( Sr ) -  336.2 MB"
    },
    {
      "id": "tt7133686",
      "type": "movie",
      "name": "Next Gen ( Hr ) -  538.2 MB"
    },
    {
      "id": "tt0316317",
      "type": "movie",
      "name": "Nick  Noel ( Hr ) -  140.3 MB"
    },
    {
      "id": "tt0316317",
      "type": "movie",
      "name": "Nick  Noel ( Sr ) -  138.8 MB"
    },
    {
      "id": "tt2312862",
      "type": "movie",
      "name": "Nicky Deuce ( Hr ) -  514.9 MB"
    },
    {
      "id": "tt2312862",
      "type": "movie",
      "name": "Nicky Deuce ( Sr ) -  351.5 MB"
    },
    {
      "id": "tt1856053",
      "type": "movie",
      "name": "Niko 02 Mali Brat Velika Frka ( H I S ) -  453.3 MB"
    },
    {
      "id": "tt0885415",
      "type": "movie",
      "name": "Niko Bozicna Potraga ( Hr ) -  458.3 MB"
    },
    {
      "id": "tt19500164",
      "type": "movie",
      "name": "Nimona ( Hr ) -  651.8 MB"
    },
    {
      "id": "tt3949660",
      "type": "movie",
      "name": "Nindza Kornjace ( Film H I S ) -  549.7 MB"
    },
    {
      "id": "tt8589698",
      "type": "movie",
      "name": "Nindza Kornjace Haos ( H i S ) -  863.1 MB"
    },
    {
      "id": "tt10521144",
      "type": "movie",
      "name": "Nocni Dnevnici ( Hr ) -  654.9 MB"
    },
    {
      "id": "tt0079635",
      "type": "movie",
      "name": "Nocturna ( Sr ) -  345.3 MB"
    },
    {
      "id": "tt0119114",
      "type": "movie",
      "name": "Nogometna Groznica ( Hr ) -  304.2 MB"
    },
    {
      "id": "tt2583814",
      "type": "movie",
      "name": "Nosorog Oto ( Sr ) -  319.5 MB"
    },
    {
      "id": "tt0105251",
      "type": "movie",
      "name": "Nova Generacija ( Hr ) -  569.5 MB"
    },
    {
      "id": "tt1964418",
      "type": "movie",
      "name": "Novi Dom ( Hr ) -  102.6 MB"
    },
    {
      "id": "tt0284362",
      "type": "movie",
      "name": "O Bozicno Drvce ( Hr ) -  209.8 MB"
    },
    {
      "id": "tt1985966",
      "type": "movie",
      "name": "Oblacno Sa Cuftama 02 ( Hr ) -  668.8 MB"
    },
    {
      "id": "tt9288748",
      "type": "movie",
      "name": "Ocev Zmaj ( Hr ) -  484.7 MB"
    },
    {
      "id": "tt12922900",
      "type": "movie",
      "name": "Odiseja ( Hr ) -  249.9 MB"
    },
    {
      "id": "tt15091284",
      "type": "movie",
      "name": "Odvazna Iva I Skriveno Blago Maglograda ( Hr ) -  673.1 MB"
    },
    {
      "id": "tt0380599",
      "type": "movie",
      "name": "Oliver Tvist ( Sr ) -  423.8 MB"
    },
    {
      "id": "tt4590256",
      "type": "movie",
      "name": "On Je Sve To ( Hr ) -  824.0 MB"
    },
    {
      "id": "tt12615474",
      "type": "movie",
      "name": "Ooops 02 Avantura Se Nastavlja ( H i S ) -  797.4 MB"
    },
    {
      "id": "tt28066777",
      "type": "movie",
      "name": "Orion I Mrak ( Hr ) -  529.6 MB"
    },
    {
      "id": "tt0848228",
      "type": "movie",
      "name": "Osvetnici ( Hr ) -  394.6 MB"
    },
    {
      "id": "tt39140662",
      "type": "movie",
      "name": "Otmica ( Hr ) -  255.8 MB"
    },
    {
      "id": "tt4105584",
      "type": "movie",
      "name": "Oto Istrazivac Dubina ( H i S ) -  505.5 MB"
    },
    {
      "id": "tt7488208",
      "type": "movie",
      "name": "Over The Moon ( Hr ) -  541.8 MB"
    },
    {
      "id": "tt12981702",
      "type": "movie",
      "name": "Ozi  Glas Sume ( Sr ) -  650.1 MB"
    },
    {
      "id": "tt1398940",
      "type": "movie",
      "name": "Palcica ( Hr ) -  123.6 MB"
    },
    {
      "id": "tt13616980",
      "type": "movie",
      "name": "Panda U Africi ( Hr ) -  699.9 MB"
    },
    {
      "id": "tt13616980",
      "type": "movie",
      "name": "Panda U Africi ( Sr ) -  590.0 MB"
    },
    {
      "id": "tt5320892",
      "type": "movie",
      "name": "Pat I Mat Film 04 ( Np ) -  423.6 MB"
    },
    {
      "id": "tt6495056",
      "type": "movie",
      "name": "Patke Selice ( H I S ) -  758.6 MB"
    },
    {
      "id": "tt3723780",
      "type": "movie",
      "name": "Patke Za Nemoguce Zadatke ( Hr ) -  735.4 MB"
    },
    {
      "id": "tt5851786",
      "type": "movie",
      "name": "Patuljci Uzvracaju Udarac ( H i S ) -  594.0 MB"
    },
    {
      "id": "tt6494344",
      "type": "movie",
      "name": "Pazi Se Carobnjaka ( Hr ) -  709.3 MB"
    },
    {
      "id": "tt6685596",
      "type": "movie",
      "name": "Pcelica Maja 02 Medene Igre ( H i S ) -  592.6 MB"
    },
    {
      "id": "tt11792512",
      "type": "movie",
      "name": "Pcelica Maja 03 Zlatno Jaje ( H i S ) -  597.8 MB"
    },
    {
      "id": "tt0356470",
      "type": "movie",
      "name": "Pepeljuga 01 ( H I S ) -  459.0 MB"
    },
    {
      "id": "tt1661199",
      "type": "movie",
      "name": "Pepeljuga 02 ( Sr ) -  329.1 MB"
    },
    {
      "id": "tt0098077",
      "type": "movie",
      "name": "Peraustrinia ( Sr ) -  469.0 MB"
    },
    {
      "id": "tt3181400",
      "type": "movie",
      "name": "Pernata Banda ( H i S ) -  571.2 MB"
    },
    {
      "id": "tt1446192",
      "type": "movie",
      "name": "Pet Legendi ( H I S ) -  757.9 MB"
    },
    {
      "id": "tt0046183",
      "type": "movie",
      "name": "Petar Pan 01 ( Sr ) -  437.4 MB"
    },
    {
      "id": "tt0316396",
      "type": "movie",
      "name": "Petar Pan 02 ( Sr ) -  328.6 MB"
    },
    {
      "id": "tt5117670",
      "type": "movie",
      "name": "Petar Zecimir 01 ( H i S ) -  852.8 MB"
    },
    {
      "id": "tt5117670",
      "type": "movie",
      "name": "Petar Zecimir 02 ( H i S ) -  798.5 MB"
    },
    {
      "id": "tt8609660",
      "type": "movie",
      "name": "Pingvin Pingo ( Sr ) -  461.2 MB"
    },
    {
      "id": "tt0332318",
      "type": "movie",
      "name": "Pinokio 3000 ( Hr ) -  453.1 MB"
    },
    {
      "id": "tt0762125",
      "type": "movie",
      "name": "Planeta 51 ( Hr ) -  468.8 MB"
    },
    {
      "id": "tt10069606",
      "type": "movie",
      "name": "Plankton ( Hr ) -  595.6 MB"
    },
    {
      "id": "tt0299172",
      "type": "movie",
      "name": "Pobuna Na Farmi ( H i S ) -  475.2 MB"
    },
    {
      "id": "tt8337264",
      "type": "movie",
      "name": "Pobuna U Kokosinjcu Zora Medaljona ( Hr ) -  586.4 MB"
    },
    {
      "id": "tt0114148",
      "type": "movie",
      "name": "Pocahontas ( Kiosk H i S ) -  344.5 MB"
    },
    {
      "id": "tt0114148",
      "type": "movie",
      "name": "Pokahontas 01 ( Sr ) -  344.6 MB"
    },
    {
      "id": "tt0143808",
      "type": "movie",
      "name": "Pokahontas 02 ( Sr ) -  328.1 MB"
    },
    {
      "id": "tt0347149",
      "type": "movie",
      "name": "Pokretni Dvorac ( Hr ) -  536.7 MB"
    },
    {
      "id": "tt4426464",
      "type": "movie",
      "name": "Polarna Avantura ( H i S ) -  650.9 MB"
    },
    {
      "id": "tt0110008",
      "type": "movie",
      "name": "Pom Poko ( Sr ) -  580.3 MB"
    },
    {
      "id": "tt0173018",
      "type": "movie",
      "name": "Poplava ( NP ) -  1.4 GB"
    },
    {
      "id": "tt0104652",
      "type": "movie",
      "name": "Porco Rosso ( Sr ) -  529.2 MB"
    },
    {
      "id": "tt2062622",
      "type": "movie",
      "name": "Postar Pat Film ( Hr ) -  399.7 MB"
    },
    {
      "id": "tt2277860",
      "type": "movie",
      "name": "Potraga za Dorom ( H i S ) -  848.3 MB"
    },
    {
      "id": "tt0327084",
      "type": "movie",
      "name": "Preko Ograde ( Hr ) -  393.8 MB"
    },
    {
      "id": "tt15575356",
      "type": "movie",
      "name": "Prestar Za Bajke 01 (2022) -  743.5 MB"
    },
    {
      "id": "tt31739491",
      "type": "movie",
      "name": "Prestar Za Bajke 02 (2022) -  876.9 MB"
    },
    {
      "id": "tt0114709",
      "type": "movie",
      "name": "Prica O Igrackama 01 ( H I S ) -  727.4 MB"
    },
    {
      "id": "tt0120363",
      "type": "movie",
      "name": "Prica O Igrackama 02 ( H I S ) -  826.7 MB"
    },
    {
      "id": "tt0435761",
      "type": "movie",
      "name": "Prica O Igrackama 03 ( H I S ) -  922.0 MB"
    },
    {
      "id": "tt1979376",
      "type": "movie",
      "name": "Prica O Igrackama 04 ( H I S ) -  818.1 MB"
    },
    {
      "id": "tt3473654",
      "type": "movie",
      "name": "Prica O Igrackama Bozicna Prica ( Hr ) -  141.5 MB"
    },
    {
      "id": "tt0499576",
      "type": "movie",
      "name": "Prica O Jacku Frostu ( Hr ) -  180.9 MB"
    },
    {
      "id": "tt8434394",
      "type": "movie",
      "name": "Prica O Leptiru ( Hr ) -  671.6 MB"
    },
    {
      "id": "tt0420238",
      "type": "movie",
      "name": "Prica O Misu Zvanom Despero ( Hr ) -  370.5 MB"
    },
    {
      "id": "tt0120794",
      "type": "movie",
      "name": "Princ Egipta ( Hr ) -  343.6 MB"
    },
    {
      "id": "tt4086018",
      "type": "movie",
      "name": "Princeva Strana Price ( H i S ) -  506.6 MB"
    },
    {
      "id": "tt0780521",
      "type": "movie",
      "name": "Princeza I Zaba ( Hr ) -  465.6 MB"
    },
    {
      "id": "tt13651628",
      "type": "movie",
      "name": "Princeza I Zmaj ( Sr ) -  696.8 MB"
    },
    {
      "id": "tt9038290",
      "type": "movie",
      "name": "Princeza Late i Magicni Vodeni Kamen ( Sr ) -  634.1 MB"
    },
    {
      "id": "tt5161658",
      "type": "movie",
      "name": "Prste(n) K Sebi ( Hr ) -  700.9 MB"
    },
    {
      "id": "tt1891905",
      "type": "movie",
      "name": "Pupijeva Potraga ( H I S ) -  583.6 MB"
    },
    {
      "id": "tt0424095",
      "type": "movie",
      "name": "Pusti Vodu Da Misevi Odu ( Hr ) -  620.6 MB"
    },
    {
      "id": "tt0327437",
      "type": "movie",
      "name": "Put Oko Sveta Za 80 Dana ( H i S ) -  542.3 MB"
    },
    {
      "id": "tt10341040",
      "type": "movie",
      "name": "Put Oko Sveta Za 80 Dana 2021 ( H i S ) -  627.2 MB"
    },
    {
      "id": "tt0138749",
      "type": "movie",
      "name": "Put U Eldorado ( Hr ) -  705.3 MB"
    },
    {
      "id": "tt1910605",
      "type": "movie",
      "name": "Rags ( H i S ).mp4 -  1.0 GB"
    },
    {
      "id": "tt5109280",
      "type": "movie",
      "name": "Raja I Poslednji Zmaj ( H i S ).mp4 -  892.5 MB"
    },
    {
      "id": "tt3876942",
      "type": "movie",
      "name": "Rajski Vrt ( Sr ).mp4 -  231.6 MB"
    },
    {
      "id": "tt3480110",
      "type": "movie",
      "name": "Rajsko Putovanje ( Sr ).mp4 -  318.1 MB"
    },
    {
      "id": "tt1192628",
      "type": "movie",
      "name": "Rango ( Hr ).mp4 -  1.1 GB"
    },
    {
      "id": "tt0216140",
      "type": "movie",
      "name": "Rarg ( Hr ).mp4 -  180.3 MB"
    },
    {
      "id": "tt0382932",
      "type": "movie",
      "name": "Ratatouille ( H I S ).mp4 -  613.6 MB"
    },
    {
      "id": "tt2865120",
      "type": "movie",
      "name": "Ratchet I Clank ( H I S ).mp4 -  576.7 MB"
    },
    {
      "id": "tt5848272",
      "type": "movie",
      "name": "Razbijac Ralf 02 ( H i S ).mp4 -  744.7 MB"
    },
    {
      "id": "tt0307453",
      "type": "movie",
      "name": "Riba Ribi Grize Rep ( Hr ).mp4 -  570.4 MB"
    },
    {
      "id": "tt4940416",
      "type": "movie",
      "name": "Ringe Ringe Raja ( H i S ).mp4 -  769.3 MB"
    },
    {
      "id": "tt1167660",
      "type": "movie",
      "name": "Rio 01 ( H I S ).mp4 -  661.3 MB"
    },
    {
      "id": "tt2357291",
      "type": "movie",
      "name": "Rio 02 ( H I S ).mp4 -  802.6 MB"
    },
    {
      "id": "tt0307384",
      "type": "movie",
      "name": "Riverdance ( Hr ).mp4 -  698.5 MB"
    },
    {
      "id": "tt0114287",
      "type": "movie",
      "name": "Rob Roj ( H i S ).mp4 -  346.1 MB"
    },
    {
      "id": "tt0786915",
      "type": "movie",
      "name": "Robin Robin ( Hr ).mp4 -  201.3 MB"
    },
    {
      "id": "tt4731008",
      "type": "movie",
      "name": "Robinson Kruso ( Hr ).mp4 -  98.0 MB"
    },
    {
      "id": "tt4731008",
      "type": "movie",
      "name": "Robinson Kruso 2016 ( H I S ).mp4 -  569.3 MB"
    },
    {
      "id": "tt21987308",
      "type": "movie",
      "name": "Roboti ( Hr ).mp4 -  537.8 MB"
    },
    {
      "id": "tt0058536",
      "type": "movie",
      "name": "Rudolf Jelen Crvenog Nosica ( H i S ).mp4 -  773.5 MB"
    },
    {
      "id": "tt0024509",
      "type": "movie",
      "name": "Rufus 01 ( H i S ).mp4 -  455.6 MB"
    },
    {
      "id": "tt5687968",
      "type": "movie",
      "name": "Rufus 02 ( H i S ).mp4 -  450.6 MB"
    },
    {
      "id": "tt0396042",
      "type": "movie",
      "name": "Ruzno Pace I Ja ( Hr ).mp4 -  387.5 MB"
    },
    {
      "id": "tt4075322",
      "type": "movie",
      "name": "Saba Mali Ratnik Velikoga Srca ( H i S ) -  938.6 MB"
    },
    {
      "id": "tt9846154",
      "type": "movie",
      "name": "Sadko ( Sr ) -  779.2 MB"
    },
    {
      "id": "tt2128499",
      "type": "movie",
      "name": "Sammy 01 ( H I S ) -  606.3 MB"
    },
    {
      "id": "tt27604215",
      "type": "movie",
      "name": "Samo Sanjaj ( Hr ) -  472.4 MB"
    },
    {
      "id": "tt0211578",
      "type": "movie",
      "name": "Sandokan ( H i S ) -  948.8 MB"
    },
    {
      "id": "tt0413895",
      "type": "movie",
      "name": "Sarlotina Mreza ( Hr ) -  1.0 GB"
    },
    {
      "id": "tt12838958",
      "type": "movie",
      "name": "Scooby Doo 2020 ( Hr ) -  915.7 MB"
    },
    {
      "id": "tt0418141",
      "type": "movie",
      "name": "Scooby Doo Cudoviste Iz Loch Nessa ( H I S ) -  607.2 MB"
    },
    {
      "id": "tt0290057",
      "type": "movie",
      "name": "Scooby Doo Kiberneticki Lov ( H i S ) -  488.2 MB"
    },
    {
      "id": "tt0044008",
      "type": "movie",
      "name": "Scrooge Bozicna Prica ( Hr ) -  806.6 MB"
    },
    {
      "id": "tt0112545",
      "type": "movie",
      "name": "Sedmi Brat ( Hr ) -  397.2 MB"
    },
    {
      "id": "tt2914892",
      "type": "movie",
      "name": "Sedmi Patuljak ( H I S ) -  563.2 MB"
    },
    {
      "id": "tt2590900",
      "type": "movie",
      "name": "Segrt Hlapic ( Hr ).mp4 -  552.9 MB"
    },
    {
      "id": "tt0400717",
      "type": "movie",
      "name": "Sezona Lova 01 ( H I S ) -  536.9 MB"
    },
    {
      "id": "tt1107365",
      "type": "movie",
      "name": "Sezona Lova 02 ( Hr ) -  513.2 MB"
    },
    {
      "id": "tt6193408",
      "type": "movie",
      "name": "Shaun The Sheep Farmageddon ( Np ) -  367.4 MB"
    },
    {
      "id": "tt2872750",
      "type": "movie",
      "name": "Shaun The Sheep Movie ( Np ) -  361.9 MB"
    },
    {
      "id": "tt15857304",
      "type": "movie",
      "name": "Shaun The Sheep The Flight Before Christmas ( Np ) -  208.9 MB"
    },
    {
      "id": "tt0298148",
      "type": "movie",
      "name": "Shrek 02 ( Hr ) -  763.5 MB"
    },
    {
      "id": "tt0413267",
      "type": "movie",
      "name": "Shrek 03 ( Hr ) -  753.2 MB"
    },
    {
      "id": "tt0892791",
      "type": "movie",
      "name": "Shrek 04 ( H i S ) -  711.5 MB"
    },
    {
      "id": "tt0897387",
      "type": "movie",
      "name": "Shrek Prvi Bozic ( Hr ) -  156.6 MB"
    },
    {
      "id": "tt0462538",
      "type": "movie",
      "name": "Simpsonovi ( Hr ) -  373.8 MB"
    },
    {
      "id": "tt0165982",
      "type": "movie",
      "name": "Sinbad Legenda O Sedam Mora ( Hr ) -  423.0 MB"
    },
    {
      "id": "tt6964940",
      "type": "movie",
      "name": "Skejterica ( Hr ) -  878.7 MB"
    },
    {
      "id": "tt12354878",
      "type": "movie",
      "name": "Slucajna Raskos Prozirnog Vodenog Rebusa ( Hr ) -  1.1 GB"
    },
    {
      "id": "tt13700528",
      "type": "movie",
      "name": "Slurps ( Np ) -  425.4 MB"
    },
    {
      "id": "tt6727816",
      "type": "movie",
      "name": "Smanjeni Bozic ( H i S ).mp4 -  572.0 MB"
    },
    {
      "id": "tt3477554",
      "type": "movie",
      "name": "Snezna Kraljica 02 ( H i S ) -  585.2 MB"
    },
    {
      "id": "tt4685554",
      "type": "movie",
      "name": "Snezna Kraljica 03 ( H I S ) -  618.3 MB"
    },
    {
      "id": "tt0056504",
      "type": "movie",
      "name": "Sodoma I Gomora ( Sr ) -  203.6 MB"
    },
    {
      "id": "tt2769896",
      "type": "movie",
      "name": "Solan I Ludvig ( Sr ) -  337.8 MB"
    },
    {
      "id": "tt0770807",
      "type": "movie",
      "name": "Sonikov Bozicni Juris ( Sr ) -  241.1 MB"
    },
    {
      "id": "tt4633694",
      "type": "movie",
      "name": "Spiderman Novi Svet ( H i S ) -  1.7 GB"
    },
    {
      "id": "tt9362722",
      "type": "movie",
      "name": "Spiderman Putovanje Kroz Spider Svijet ( H i S ) -  1.9 GB"
    },
    {
      "id": "tt12988016",
      "type": "movie",
      "name": "Sretan Bozic ( Hr ) -  233.8 MB"
    },
    {
      "id": "tt6182908",
      "type": "movie",
      "name": "Stopalici ( Hr ) -  555.6 MB"
    },
    {
      "id": "tt0472181",
      "type": "movie",
      "name": "Strumpfovi 01 ( H I S ) -  785.0 MB"
    },
    {
      "id": "tt18069420",
      "type": "movie",
      "name": "Strumpfovi 02 ( H I S ) -  771.8 MB"
    },
    {
      "id": "tt18069420",
      "type": "movie",
      "name": "Strumpfovi 2025 ( H I S ).mp4 -  851.3 MB"
    },
    {
      "id": "tt2958484",
      "type": "movie",
      "name": "Strumpfovi Legenda O Tajanstvenom Jahacu ( Hr ) -  135.7 MB"
    },
    {
      "id": "tt2398241",
      "type": "movie",
      "name": "Strumpfovi Skriveno Selo ( H i S ) -  928.6 MB"
    },
    {
      "id": "tt6718170",
      "type": "movie",
      "name": "Super Mario Bros 2023 ( H i S ) -  1.0 GB"
    },
    {
      "id": "tt6314690",
      "type": "movie",
      "name": "Super Panda ( H I S ) -  542.0 MB"
    },
    {
      "id": "tt29362046",
      "type": "movie",
      "name": "Super Spori Super Mocni ( Hr ) -  564.7 MB"
    },
    {
      "id": "tt7178640",
      "type": "movie",
      "name": "Super Zeka ( Sr ) -  447.8 MB"
    },
    {
      "id": "tt0406375",
      "type": "movie",
      "name": "Svemirska Avantura 02 ( Hr ) -  364.7 MB"
    },
    {
      "id": "tt0406375",
      "type": "movie",
      "name": "Svemirska Avantura 02 ( Sr ) -  708.6 MB"
    },
    {
      "id": "tt1272051",
      "type": "movie",
      "name": "Svemirska Avantura 03 ( Sr ) -  703.8 MB"
    },
    {
      "id": "tt0117705",
      "type": "movie",
      "name": "Svemirski Basket ( Sr ) -  517.3 MB"
    },
    {
      "id": "tt0117705",
      "type": "movie",
      "name": "Svemirski Basket 2021 ( H i S ) -  1.3 GB"
    },
    {
      "id": "tt0096787",
      "type": "movie",
      "name": "Svi Psi Idu U Raj ( H i S ) -  684.5 MB"
    },
    {
      "id": "tt10298810",
      "type": "movie",
      "name": "Svjetlosni ( Hr ) -  754.9 MB"
    },
    {
      "id": "tt5817548",
      "type": "movie",
      "name": "Tabaluga ( H i S ) -  752.0 MB"
    },
    {
      "id": "tt14855468",
      "type": "movie",
      "name": "Taj Bozic ( Hr ) -  670.3 MB"
    },
    {
      "id": "tt5815016",
      "type": "movie",
      "name": "Tajna Izgubljenog Kraljevstva ( Sr ) -  401.5 MB"
    },
    {
      "id": "tt0130134",
      "type": "movie",
      "name": "Tajna O Anastasiji ( Hr ) -  283.4 MB"
    },
    {
      "id": "tt0218589",
      "type": "movie",
      "name": "Tajna O Mulan ( Hr ) -  303.5 MB"
    },
    {
      "id": "tt5113040",
      "type": "movie",
      "name": "Tajni Zivot Ljubimaca 02 ( H i S ) -  749.2 MB"
    },
    {
      "id": "tt7886614",
      "type": "movie",
      "name": "Tajni Zivot Macaka ( Hr ) -  703.4 MB"
    },
    {
      "id": "tt0120855",
      "type": "movie",
      "name": "Tarzan 2013 ( Hr ) -  997.8 MB"
    },
    {
      "id": "tt31123288",
      "type": "movie",
      "name": "The Casagrandes Film ( Hr ) -  784.0 MB"
    },
    {
      "id": "tt3148834",
      "type": "movie",
      "name": "The House Of Magic ( H i S ) -  545.9 MB"
    },
    {
      "id": "tt0120913",
      "type": "movie",
      "name": "Titan A.E. ( Hr ) -  521.7 MB"
    },
    {
      "id": "tt0487176",
      "type": "movie",
      "name": "Tom  Jerry Brzi I Dlakavi ( Hr ) -  470.4 MB"
    },
    {
      "id": "tt0303151",
      "type": "movie",
      "name": "Tom  Jerry Carobni Prsten ( Hr ) -  272.8 MB"
    },
    {
      "id": "tt0808508",
      "type": "movie",
      "name": "Tom  Jerry Gusari ( Hr ) -  424.7 MB"
    },
    {
      "id": "tt1361336",
      "type": "movie",
      "name": "Tom i Dzeri 2021 ( H i S ) -  1.0 GB"
    },
    {
      "id": "tt1977087",
      "type": "movie",
      "name": "Tom Sojer ( Hr ) -  257.9 MB"
    },
    {
      "id": "tt1977087",
      "type": "movie",
      "name": "Tom Sojer ( Sr ) -  252.2 MB"
    },
    {
      "id": "tt0375154",
      "type": "movie",
      "name": "Tristan I Izolda ( Hr ) -  390.8 MB"
    },
    {
      "id": "tt1679335",
      "type": "movie",
      "name": "Trolovi ( H i S ) -  606.7 MB"
    },
    {
      "id": "tt14362112",
      "type": "movie",
      "name": "Trolovi Bend Na Okupu ( H i S ) -  1010.3 MB"
    },
    {
      "id": "tt0498396",
      "type": "movie",
      "name": "Tudumi ( Hr ) -  770.4 MB"
    },
    {
      "id": "tt0269988",
      "type": "movie",
      "name": "Tukiki ( Sr ) -  120.4 MB"
    },
    {
      "id": "tt8456190",
      "type": "movie",
      "name": "Tuljani Specijalci ( Hr ) -  571.1 MB"
    },
    {
      "id": "tt1860353",
      "type": "movie",
      "name": "Turbo ( H I S ) -  663.6 MB"
    },
    {
      "id": "tt5726616",
      "type": "movie",
      "name": "Tvoje Ime ( Sr ) -  545.2 MB"
    },
    {
      "id": "tt5378092",
      "type": "movie",
      "name": "Ukradena Princeza ( H i S ).mp4 -  933.0 MB"
    },
    {
      "id": "tt1552428",
      "type": "movie",
      "name": "Ulica Sezam ( Hr ).mp4 -  283.6 MB"
    },
    {
      "id": "tt4265568",
      "type": "movie",
      "name": "Ultraman 01 ( Sr ).mp4 -  609.3 MB"
    },
    {
      "id": "tt9471678",
      "type": "movie",
      "name": "Ultraman Uspon ( Hr ).mp4 -  905.1 MB"
    },
    {
      "id": "tt3411432",
      "type": "movie",
      "name": "Ups Noa Je Otisao ( H i S ).mp4 -  521.0 MB"
    },
    {
      "id": "tt1210117",
      "type": "movie",
      "name": "Urmel ( Sr ).mp4 -  139.4 MB"
    },
    {
      "id": "tt0412677",
      "type": "movie",
      "name": "Uskrs U Zemlji Zeceva ( Hr ).mp4 -  209.3 MB"
    },
    {
      "id": "tt6484954",
      "type": "movie",
      "name": "Uzbuna Na Zelenom Vrhu ( Hr ).mp4 -  451.8 MB"
    },
    {
      "id": "tt3521164",
      "type": "movie",
      "name": "Vajana 01 ( H i S ).mp4 -  822.8 MB"
    },
    {
      "id": "tt13622970",
      "type": "movie",
      "name": "Vajana 02 ( H i S ).mp4 -  1.1 GB"
    },
    {
      "id": "tt0361089",
      "type": "movie",
      "name": "Valiant ( Hr ).mp4 -  381.8 MB"
    },
    {
      "id": "tt4729560",
      "type": "movie",
      "name": "Vampirko ( H i S ).mp4 -  753.2 MB"
    },
    {
      "id": "tt1800241",
      "type": "movie",
      "name": "Varalice ( Hr ).mp4 -  822.5 MB"
    },
    {
      "id": "tt2954570",
      "type": "movie",
      "name": "Vasilisa Prekrasna ( Sr ).mp4 -  132.2 MB"
    },
    {
      "id": "tt8354218",
      "type": "movie",
      "name": "Vatreno Srce ( H i S ).mp4 -  831.0 MB"
    },
    {
      "id": "tt3691740",
      "type": "movie",
      "name": "Veliki Dobrocudni Dzin 2016 ( H i S ).mp4 -  1.0 GB"
    },
    {
      "id": "tt0146833",
      "type": "movie",
      "name": "Veliki Strah ( Sr ).mp4 -  160.3 MB"
    },
    {
      "id": "tt9719256",
      "type": "movie",
      "name": "Veliko Putovanje 02 Specijalna Dostava ( Hr ) -  820.2 MB"
    },
    {
      "id": "tt9719256",
      "type": "movie",
      "name": "Veliko Putovanje 02 Specijalna Dostava ( Sr ) -  850.8 MB"
    },
    {
      "id": "tt0272101",
      "type": "movie",
      "name": "Veseli Dozivljaji Cudesnih Mrava ( Hr ).mp4 -  645.1 MB"
    },
    {
      "id": "tt0086590",
      "type": "movie",
      "name": "Vetar U Vrbaku ( Hr ).mp4 -  313.5 MB"
    },
    {
      "id": "tt0086590",
      "type": "movie",
      "name": "Vetar U Vrbaku ( Sr ).mp4 -  647.9 MB"
    },
    {
      "id": "tt8065768",
      "type": "movie",
      "name": "Viking Vik i Carobni Mac ( H i S ).mp4 -  678.3 MB"
    },
    {
      "id": "tt15565714",
      "type": "movie",
      "name": "Vilenjaci ( Sr ).mp4 -  394.3 MB"
    },
    {
      "id": "tt6338498",
      "type": "movie",
      "name": "Vivo ( Hr ).mp4 -  734.1 MB"
    },
    {
      "id": "tt0268695",
      "type": "movie",
      "name": "Vremeplov ( Hr ) -  449.5 MB"
    },
    {
      "id": "tt0398286",
      "type": "movie",
      "name": "Vrlo Zapetljana Prica ( Tangled ) ( Hr ) -  444.5 MB"
    },
    {
      "id": "tt0131636",
      "type": "movie",
      "name": "Vuk ( Hr ) -  849.3 MB"
    },
    {
      "id": "tt22478818",
      "type": "movie",
      "name": "William Tell ( Hr ).mp4 -  191.5 MB"
    },
    {
      "id": "tt1618450",
      "type": "movie",
      "name": "Winx Carobna Avantura ( H I S ).mp4 -  853.0 MB"
    },
    {
      "id": "tt1206585",
      "type": "movie",
      "name": "Winx Club Tajna Izgubljenog Kraljevstva ( H I S ).mp4 -  645.5 MB"
    },
    {
      "id": "tt6166392",
      "type": "movie",
      "name": "Wonka ( H i S ).mp4 -  901.7 MB"
    },
    {
      "id": "tt4225608",
      "type": "movie",
      "name": "Yankee Doodle ( Hr ).mp4 -  112.0 MB"
    },
    {
      "id": "tt0403703",
      "type": "movie",
      "name": "Yu Gi Oh Film ( Hr ).mp4 -  510.1 MB"
    },
    {
      "id": "tt0403703",
      "type": "movie",
      "name": "Yu Gi Oh Film ( Sr ).mp4 -  412.4 MB"
    },
    {
      "id": "tt1545319",
      "type": "movie",
      "name": "Zaboglavi Zivko ( Hr ) -  638.3 MB"
    },
    {
      "id": "tt0146860",
      "type": "movie",
      "name": "Zacarani ( Hr ) -  1.0 GB"
    },
    {
      "id": "tt0173886",
      "type": "movie",
      "name": "Zacarani Grad ( Sr ) -  616.5 MB"
    },
    {
      "id": "tt0092067",
      "type": "movie",
      "name": "Zamak Na Nebu ( Sr ) -  618.2 MB"
    },
    {
      "id": "tt1488181",
      "type": "movie",
      "name": "Zambezija ( H I S ) -  533.5 MB"
    },
    {
      "id": "tt0406375",
      "type": "movie",
      "name": "Zathura Svemirska Avantura ( Hr ) -  663.6 MB"
    },
    {
      "id": "tt0376105",
      "type": "movie",
      "name": "Zebra Trkacica ( H i S ) -  1.1 GB"
    },
    {
      "id": "tt12631784",
      "type": "movie",
      "name": "Zecija Akademija Nemoguca Misijaja ( Sr ) -  586.1 MB"
    },
    {
      "id": "tt12532368",
      "type": "movie",
      "name": "Zecko Kos I Tajna Mrkog Hrcka ( Hr ) -  656.8 MB"
    },
    {
      "id": "tt0201359",
      "type": "movie",
      "name": "Zelja ( H i S ) -  792.2 MB"
    },
    {
      "id": "tt13320662",
      "type": "movie",
      "name": "Zemlja Sna ( Hr ) -  1.0 GB"
    },
    {
      "id": "tt4110400",
      "type": "movie",
      "name": "Zip I Zap ( Sr ) -  349.7 MB"
    },
    {
      "id": "tt0120623",
      "type": "movie",
      "name": "Zivot Buba ( H i S ) -  784.9 MB"
    },
    {
      "id": "tt0145799",
      "type": "movie",
      "name": "Zlatna Antilopa ( Hr ) -  282.2 MB"
    },
    {
      "id": "tt0145799",
      "type": "movie",
      "name": "Zlatna Antilopa ( Sr ) -  154.8 MB"
    },
    {
      "id": "tt1086780",
      "type": "movie",
      "name": "Zlatokosa ( Hr ) -  253.7 MB"
    },
    {
      "id": "tt5562070",
      "type": "movie",
      "name": "Zmaj Iz Cajnika ( Hr ) -  586.7 MB"
    },
    {
      "id": "tt2948356",
      "type": "movie",
      "name": "Zootopia ( H I S ) -  619.4 MB"
    },
    {
      "id": "tt0069197",
      "type": "movie",
      "name": "Zov Divljine ( H I S ) -  288.3 MB"
    },
    {
      "id": "tt0069197",
      "type": "movie",
      "name": "Zov Divljine ( The Wild ) ( H i S ) -  813.4 MB"
    },
    {
      "id": "tt0371606",
      "type": "movie",
      "name": "Zuta Minuta ( H i S ) -  704.6 MB"
    },
    {
      "id": "tt0116583",
      "type": "movie",
      "name": "Zvonar Crkve Notre Dame ( Hr ) -  290.6 MB"
    },
    {
      "id": "tt0823671",
      "type": "movie",
      "name": "Zvoncica 01 ( H i S ) -  683.8 MB"
    },
    {
      "id": "tt1216516",
      "type": "movie",
      "name": "Zvoncica 02 Izgubljeno Blago ( H I S ) -  747.4 MB"
    },
    {
      "id": "tt1216515",
      "type": "movie",
      "name": "Zvoncica 03 Velicanstveno Vilinsko Spasavanje ( H i S ) -  604.7 MB"
    },
    {
      "id": "tt1217213",
      "type": "movie",
      "name": "Zvoncica 04 Tajna Krila ( H i S ) -  731.5 MB"
    },
    {
      "id": "tt2483260",
      "type": "movie",
      "name": "Zvoncica 05 Gusarska Vila ( H I S ) -  733.4 MB"
    },
    {
      "id": "tt3120408",
      "type": "movie",
      "name": "Zvoncica 06 Cudoviste Iz Nigdjezemske ( H i S ) -  666.0 MB"
    }
  ]
}
